PyTistory/__init__.py
PyTistory/auto_auth.py
PyTistory/request_api.py
Python_Tistory-1.0.0.dist-info/LICENSE
Python_Tistory-1.0.0.dist-info/METADATA
Python_Tistory-1.0.0.dist-info/WHEEL
Python_Tistory-1.0.0.dist-info/top_level.txt
Python_Tistory-1.0.0.dist-info/RECORD
