Metadata-Version: 2.1
Name: Python-Tistory
Version: 1.0.0
Summary: Tistory Open API Python Wrapper
Author: Hyeonseok Cha
Author-email: t3nderex@gmail.com
License-File: LICENSE
Requires-Dist: webdriver-manager (==3.8.3)
Requires-Dist: requests (==2.28.1)
Requires-Dist: selenium (==4.4.3)
